nomopy/__init__.py
nomopy/fhmm/FHMM.py
nomopy/fhmm/__init__.py
nomopy/fhmm/convergence_monitor.py
nomopy/fhmm/exact_hessian.py
nomopy/fhmm/numba_utilities.py
nomopy/hos/__init__.py
nomopy/hos/secondspectrum.py
nomopy/noise/__init__.py
nomopy/noise/tlf.py
nomopy-0.1.2.dist-info/licenses/LICENSE
nomopy-0.1.2.dist-info/METADATA
nomopy-0.1.2.dist-info/WHEEL
nomopy-0.1.2.dist-info/top_level.txt
nomopy-0.1.2.dist-info/RECORD
