Metadata-Version: 2.4
Name: nomopy
Version: 0.1.2
Summary: Noise Modeling in Python
Author-email: "Dylan Albrecht, Toby Jacobson, Rohith Vudatha" <nomopy@sandia.gov>
License-Expression: MIT
Project-URL: Documentation, https://nomopy.readthedocs.io
Project-URL: Repository, https://github.com/sandialabs/nomopy
Classifier: Development Status :: 4 - Beta
Classifier: Intended Audience :: Science/Research
Classifier: Intended Audience :: Developers
Classifier: Programming Language :: Python
Classifier: Programming Language :: Python :: 3.7
Classifier: Programming Language :: Python :: 3.8
Classifier: Topic :: Software Development
Classifier: Topic :: Scientific/Engineering
Classifier: Operating System :: Microsoft :: Windows
Classifier: Operating System :: POSIX
Classifier: Operating System :: Unix
Classifier: Operating System :: MacOS
Requires-Python: >=3.7
License-File: LICENSE
Requires-Dist: numpy>=1.11.1
Requires-Dist: scipy>=1.5.2
Requires-Dist: matplotlib>=1.5.1
Requires-Dist: scikit-learn>=0.23.2
Requires-Dist: joblib>=0.17.0
Requires-Dist: autograd>=1.3
Provides-Extra: tests
Requires-Dist: pytest; extra == "tests"
Requires-Dist: numpy; extra == "tests"
Requires-Dist: hypothesis; extra == "tests"
Dynamic: license-file
